imperatoraPY/__init__.py
imperatoraPY/client.py
imperatoraPY/exceptions.py
imperatoraPY/objects.py
imperatoraPY/request.py
imperatoraPY-1.4.4.dist-info/LICENSE
imperatoraPY-1.4.4.dist-info/METADATA
imperatoraPY-1.4.4.dist-info/WHEEL
imperatoraPY-1.4.4.dist-info/top_level.txt
imperatoraPY-1.4.4.dist-info/RECORD
