Metadata-Version: 2.1
Name: imperatoraPY
Version: 1.4.4
Summary: An API wrapper for the Imperator API
Home-page: https://github.com/myerfire/imperatoraPY
Author: myerfire
Author-email: realmyerfire@gmail.com
License: UNKNOWN
Platform: UNKNOWN
Classifier: Programming Language :: Python :: 3
Classifier: License :: OSI Approved :: MIT License
Classifier: Operating System :: OS Independent
Requires-Python: >=3.6
